pipeline_anomaly_dimension_class/__init__.py
pipeline_anomaly_dimension_class-1.1.dist-info/LICENSE
pipeline_anomaly_dimension_class-1.1.dist-info/METADATA
pipeline_anomaly_dimension_class-1.1.dist-info/WHEEL
pipeline_anomaly_dimension_class-1.1.dist-info/top_level.txt
pipeline_anomaly_dimension_class-1.1.dist-info/RECORD
