Metadata-Version: 2.1
Name: pipeline_anomaly_dimension_class
Version: 1.1
Summary: Python class for pipeline anomaly dimension classification
Home-page: https://github.com/vb64/pipeline.anomaly.dimension.class
Author: Vitaly Bogomolov
Author-email: mail@vitaly-bogomolov.ru
Project-URL: Bug Tracker, https://github.com/vb64/pipeline.anomaly.dimension.classy/issues
Classifier: Programming Language :: Python
Classifier: License :: OSI Approved :: MIT License
Classifier: Operating System :: OS Independent
License-File: LICENSE
